ipyspeck/__init__.py
ipyspeck/_version.py
ipyspeck/speck.py
ipyspeck/labextension/package.json
ipyspeck/labextension/static/122.fe6da30db2412ea6f028.js
ipyspeck/labextension/static/509.ba3680d8e583662f1b72.js
ipyspeck/labextension/static/543.bb5ffe6c34fc58c5e7ad.js
ipyspeck/labextension/static/543.bb5ffe6c34fc58c5e7ad.js.LICENSE.txt
ipyspeck/labextension/static/885.061f4d252527a8bb3be8.js
ipyspeck/labextension/static/remoteEntry.d6b1d9a7c1c1f180bffa.js
ipyspeck/labextension/static/style.js
ipyspeck/labextension/static/third-party-licenses.json
ipyspeck/nbextension/index.js
ipyspeck/nbextension/index.js.LICENSE.txt
ipyspeck/nbextension/index.js.map
ipyspeck/stspeck/__init__.py
ipyspeck/stspeck/frontend/.env
ipyspeck/stspeck/frontend/.eslintcache
ipyspeck/stspeck/frontend/.prettierrc
ipyspeck/stspeck/frontend/package-lock.json
ipyspeck/stspeck/frontend/package.json
ipyspeck/stspeck/frontend/tsconfig.json
ipyspeck/stspeck/frontend/public/bootstrap.min.css
ipyspeck/stspeck/frontend/public/index.html
ipyspeck/stspeck/frontend/src/colors.js
ipyspeck/stspeck/frontend/src/const.js
ipyspeck/stspeck/frontend/src/cube.js
ipyspeck/stspeck/frontend/src/elements.js
ipyspeck/stspeck/frontend/src/gl-matrix.js
ipyspeck/stspeck/frontend/src/index.tsx
ipyspeck/stspeck/frontend/src/interactions.js
ipyspeck/stspeck/frontend/src/react-app-env.d.ts
ipyspeck/stspeck/frontend/src/renderer.js
ipyspeck/stspeck/frontend/src/shaders.js
ipyspeck/stspeck/frontend/src/system.js
ipyspeck/stspeck/frontend/src/view.js
ipyspeck/stspeck/frontend/src/webgl.js
ipyspeck-0.7.1.data/data/share/jupyter/labextensions/ipyspeck/package.json
ipyspeck-0.7.1.data/data/share/jupyter/labextensions/ipyspeck/static/122.fe6da30db2412ea6f028.js
ipyspeck-0.7.1.data/data/share/jupyter/labextensions/ipyspeck/static/509.ba3680d8e583662f1b72.js
ipyspeck-0.7.1.data/data/share/jupyter/labextensions/ipyspeck/static/543.bb5ffe6c34fc58c5e7ad.js
ipyspeck-0.7.1.dist-info/METADATA
ipyspeck-0.7.1.dist-info/WHEEL
ipyspeck-0.7.1.dist-info/licenses/LICENSE
ipyspeck-0.7.1.dist-info/licenses/LICENSE.txt
ipyspeck-0.7.1.dist-info/RECORD
