Metadata-Version: 2.4
Name: ipyspeck
Version: 0.7.1
Summary: Speck Jupyter Widget
Project-URL: Homepage, https://github.com/denphi/speck
Project-URL: Repository, https://github.com/denphi/speck
Project-URL: Documentation, https://github.com/denphi/speck/blob/master/widget/ipyspeck/README.md
Project-URL: Bug Tracker, https://github.com/denphi/speck/issues
Author-email: "Daniel Mejia (Denphi)" <denphi@denphi.com>
License: This is free and unencumbered software released into the public domain.
License-File: LICENSE
License-File: LICENSE.txt
Keywords: Chemistry,IPython,Jupyter,JupyterLab,Molecule,Visualization,Widgets
Classifier: Framework :: Jupyter
Classifier: Framework :: Jupyter :: JupyterLab
Classifier: Framework :: Jupyter :: JupyterLab :: 3
Classifier: Framework :: Jupyter :: JupyterLab :: 4
Classifier: Intended Audience :: Developers
Classifier: Intended Audience :: Science/Research
Classifier: License :: OSI Approved :: BSD License
Classifier: Programming Language :: Python
Classifier: Programming Language :: Python :: 3
Classifier: Programming Language :: Python :: 3.9
Classifier: Programming Language :: Python :: 3.10
Classifier: Programming Language :: Python :: 3.11
Classifier: Programming Language :: Python :: 3.12
Classifier: Topic :: Scientific/Engineering :: Chemistry
Classifier: Topic :: Scientific/Engineering :: Visualization
Requires-Python: >=3.9
Requires-Dist: ipywidgets>=7.0.0
Provides-Extra: docs
Requires-Dist: jupyter-sphinx; extra == 'docs'
Requires-Dist: nbsphinx; extra == 'docs'
Requires-Dist: nbsphinx-link; extra == 'docs'
Requires-Dist: pypandoc; extra == 'docs'
Requires-Dist: pytest-check-links; extra == 'docs'
Requires-Dist: recommonmark; extra == 'docs'
Requires-Dist: sphinx-rtd-theme; extra == 'docs'
Requires-Dist: sphinx>=1.5; extra == 'docs'
Provides-Extra: examples
Provides-Extra: test
Requires-Dist: nbval; extra == 'test'
Requires-Dist: pytest-cov; extra == 'test'
Requires-Dist: pytest>=6.0; extra == 'test'
